GeminiMotorDrive.py
GeminiMotorDrive/utilities.py
GeminiMotorDrive/__init__.py
GeminiMotorDrive/drivers.py
GeminiMotorDrive/compilers/__init__.py
GeminiMotorDrive/compilers/move_sequence.py
GeminiMotorDrive-0.2.dist-info/metadata.json
GeminiMotorDrive-0.2.dist-info/RECORD
GeminiMotorDrive-0.2.dist-info/METADATA
GeminiMotorDrive-0.2.dist-info/top_level.txt
GeminiMotorDrive-0.2.dist-info/WHEEL
GeminiMotorDrive-0.2.dist-info/DESCRIPTION.rst
