Metadata-Version: 2.0
Name: GeminiMotorDrive
Version: 0.2
Summary: Utilities to control Parker Hannifin Gemini stepper/servo motor drives.
Home-page: https://github.com/frejanordsiek/GeminiMotorDrive
Author: Freja Nordsiek
Author-email: fnordsie at gmail dt com
License: Apache
Keywords: Parker Hannifin Gemini stepper servo motor
Platform: UNKNOWN
Classifier: Programming Language :: Python :: 3
Classifier: Development Status :: 3 - Alpha
Classifier: License :: OSI Approved :: Apache Software License
Classifier: Operating System :: OS Independent
Classifier: Intended Audience :: Manufacturing
Classifier: Intended Audience :: Science/Research
Classifier: Topic :: System :: Hardware :: Hardware Drivers
Requires: serial
